<?xml version="1.0" encoding="UTF-8"?>
<!DOCTYPE suite SYSTEM "https://testng.org/testng-1.0.dtd">
<suite thread-count="3" name="Suite" parallel="tests">
	<test name="Chrome Test">
		<parameter name="bName" value="ch"></parameter>
		<parameter name="uName" value="admin"></parameter>
		<parameter name="pwd" value="manager"></parameter>
		<classes>
			<class name="org.testCases.ParameterEx" />
		</classes>
	</test> <!-- ParameterEx -->

	<test name="Firefox Test">
		<parameter name="bName" value="fi"></parameter>
		<parameter name="uName" value="admin"></parameter>
		<parameter name="pwd" value="manager"></parameter>
		<classes>
			<class name="org.testCases.ParameterEx" />
		</classes>
	</test> <!-- ParameterEx -->
</suite> <!-- Suite -->
